[{"Name": "Shugaa", "Rating": "4.3", "votes": "336", "location": " 28 D, Sushant Shopping Arcade, Near Huda City Center Metro Station, Phase 1, Sushant Lok, Gurgaon", "Cuisines: ": "Bakery, Desserts", "hours": "9:30am\u20139pm(Mon-Sat),Closed(Sun)", "Cost for two": "\u20b9500", "Featured in: ": "Sweet Tooth"}, {"Name": "Modern Thela", "Rating": "3.7", "votes": "116", "location": " Shop C 70, Ground Floor, RDC, Raj Nagar, Ghaziabad", "Cuisines: ": "North Indian, Chinese, Fast Food, Mughlai", "hours": "11:30am\u201311pm(Mon-Sun)", "Cost for two": "\u20b9600", "Featured in: ": "Get flat 30% OFF"}, {"Name": "VIP Sweets", "Rating": "3.5", "votes": "41", "location": " Shop 54, The Shopping Mall, Arjun Marg, DLF Phase 1, Gurgaon", "Cuisines: ": "Mithai, Street Food", "hours": "10am\u20139:30pm(Mon-Sun)", "Cost for two": "\u20b9350", "Featured in: ": "Get flat 30% OFF"}, {"Name": "Waka Waka The Nightclub", "Rating": "NEW", "votes": "41", "location": " Bristol Hotel, Sector 26, Near Sikandarpur Metro Station, DLF Phase 1, Gurgaon", "Cuisines: ": "Bar Food, North Indian, Chinese", "hours": "10pm\u20135am(Mon-Sun)", "Cost for two": "\u20b92,000", "Featured in: ": "Get flat 30% OFF"}, {"Name": "Mr. Pao", "Rating": "3.6", "votes": "24", "location": " Plot 113, Lower Ground Floor & Ground Floor, Sikanderpur Ghosi, MG Road, Gurgaon", "Cuisines: ": "Street Food, North Indian", "hours": "11am\u20132am(Mon-Sun)", "Cost for two": "\u20b9250", "Featured in: ": "Get flat 30% OFF"}, {"Name": "Shahenshah", "Rating": "3.7", "votes": "171", "location": " Shop 1/2, 1st Floor, Opposite Pillar 226, Hoshiarpur Market, Sector 51, Noida", "Cuisines: ": "North Indian, Mughlai, Chinese", "hours": "11am\u201312midnight(Mon-Sun)", "Cost for two": "\u20b9500", "Featured in: ": "Get flat 30% OFF"}, {"Name": "Hunger Nation", "Rating": "3.6", "votes": "37", "location": " Ground Floor, Outside Chowringhee Lane, TDI Paragaon Mall, Rajouri Garden, New Delhi", "Cuisines: ": "Fast Food, Chinese, Rolls, North Indian", "hours": "10am\u201310:30pm(Mon-Sun)", "Cost for two": "\u20b9500", "Featured in: ": "Get flat 30% OFF"}, {"Name": "Hoggers", "Rating": "NEW", "votes": "37", "location": " UB-100, Jawahar Nagar, Kamla Nagar, New Delhi", "Cuisines: ": "Fast Food, Momos, Rolls", "hours": "11:30am\u201310:30pm(Mon-Sun)", "Cost for two": "\u20b9250", "Featured in: ": "Get flat 30% OFF"}, {"Name": "Tasty Bytes", "Rating": "3.6", "votes": "283", "location": " Shop 39, Ashoka Enclave 2, Sector 37, Faridabad", "Cuisines: ": "North Indian, Chinese", "hours": "11am\u201311pm(Mon-Sun)", "Cost for two": "\u20b9200", "Featured in: ": "Get flat 30% OFF"}, {"Name": "Chur Chur Naan Wale", "Rating": "3.3", "votes": "67", "location": " C 63, RDC, Raj Nagar, Ghaziabad", "Cuisines: ": "North Indian, South Indian, Chinese", "hours": "11am\u201312midnight(Mon-Sun)", "Cost for two": "\u20b9400", "Featured in: ": "Get flat 30% OFF"}, {"Name": "Shree Bikaner Misthan Bhandar", "Rating": "3.4", "votes": "99", "location": " U-1/4, Road 1, Behind RBS Building, ~ DLF Phase 3, Gurgaon", "Cuisines: ": "Street Food, Mithai", "hours": "10am\u201310pm(Mon-Sun)", "Cost for two": "\u20b9300", "Featured in: ": "Get flat 30% OFF"}, {"Name": "Vadapav King", "Rating": "-", "votes": "99", "location": " Shop 7, Harishchand Market, Sarfabad, Sector 73, Near Sector 72, Noida", "Cuisines: ": "Street Food", "hours": "11am\u20132am(Mon-Sun)", "Cost for two": "\u20b9150", "Featured in: ": "Get flat 30% OFF"}, {"Name": "Flaming Tadka", "Rating": "3.4", "votes": "15", "location": " Shop 3, Flat 50, Pocket I 1, Near Rohan Bansal & Associates, Rohini, New Delhi", "Cuisines: ": "North Indian, Momos, Rolls", "hours": "12noon\u201310:30pm(Mon-Sun)", "Cost for two": "\u20b9350", "Featured in: ": "Get flat 30% OFF"}, {"Name": "Black Bowl", "Rating": "4.1", "votes": "139", "location": " 01, Plot 8, Golf City, Gautam Buddha Nagar, Sector 76, Near Sector 72, Noida", "Cuisines: ": "Chinese", "hours": "12noon\u201311:30pm(Mon-Sun)", "Cost for two": "\u20b9350", "Featured in: ": "Get flat 30% OFF"}, {"Name": "Gyan Di Hatti", "Rating": "3.7", "votes": "127", "location": " Main Shivaji College Road, Raghuvir Nagar, Near Tagore Garden, New Delhi", "Cuisines: ": "North Indian", "hours": "11am\u201310:30pm(Mon-Sun)", "Cost for two": "\u20b9200", "Featured in: ": "Get flat 30% OFF"}]