[{"Name": "Passtou", "Rating": "3.8", "votes": "108", "location": " B 1 /4, Mahatma Gandhi Marg, New Ashok Nagar, Vasundhra Enclave, New Delhi", "Cuisines: ": "North Indian, Chinese, Fast Food", "hours": "7:30am\u20131am(Mon-Sun)", "Cost for two": "\u20b9500"}, {"Name": "Sakley's The Mountain Cafe", "Rating": "4.1", "votes": "1432", "location": " SF-93, 1st Floor, DLF Galleria, DLF Phase 4, Gurgaon", "Cuisines: ": "Cafe, Italian, Continental, Fast Food", "hours": "11am\u201311pm(Mon-Sun)", "Cost for two": "\u20b91,300", "Featured in: ": "Great Cafes"}, {"Name": "Prego - The Westin Gurgaon", "Rating": "4.0", "votes": "731", "location": " The Westin Hotel, Sector 29, Gurgaon", "Cuisines: ": "Italian", "hours": "12noon\u201312midnight(Mon-Sun)", "Cost for two": "\u20b94,000", "Featured in: ": "Ladies' Luncheon, Best Pizza Places In Town, Luxury Dining"}, {"Name": "Waffle Crush", "Rating": "4.2", "votes": "158", "location": " C 19, Block E, Mandir Marg, Krishna Nagar, New Delhi", "Cuisines: ": "Fast Food, Desserts, Beverages", "hours": "11am\u201311pm(Mon-Sun)", "Cost for two": "\u20b9400", "Featured in: ": "Ladies' Luncheon, Best Pizza Places In Town, Luxury Dining"}, {"Name": "Sticky Rice", "Rating": "3.9", "votes": "234", "location": " Shop 28, Central Market, Punjabi Bagh, New Delhi", "Cuisines: ": "Asian, Japanese", "hours": "12:30pm\u201311pm(Mon,Tue,Wed,Thu,Sun),12:30pm...", "Cost for two": "\u20b91,500", "Featured in: ": "Ladies' Luncheon, Best Pizza Places In Town, Luxury Dining"}, {"Name": "D'Momo Factory", "Rating": "4.1", "votes": "308", "location": " Shop G-11, Plot 1, Aditya Complex, KP Block, Community Center, Maurya Enclave, Pitampura, New Delhi", "Cuisines: ": "Chinese, Thai, Momos, Fast Food", "hours": "11am\u201311pm(Mon,Wed,Thu,Fri,Sat,Sun),Closed...", "Cost for two": "\u20b9500", "Featured in: ": "Ladies' Luncheon, Best Pizza Places In Town, Luxury Dining"}, {"Name": "Handsome Courtyard", "Rating": "4.0", "votes": "50", "location": " Plot 1, Khasra 261, Kohinoor Enclave, Western Marg, Saidulajab, Saket, New Delhi", "Cuisines: ": "North Indian, Chinese, Italian, Continental, Fast Food", "hours": "12noon\u20134am(Mon-Sun)", "Cost for two": "\u20b91,200", "Featured in: ": "Ladies' Luncheon, Best Pizza Places In Town, Luxury Dining"}, {"Name": "High On Health", "Rating": "4.0", "votes": "34", "location": " 730, Shakti Khand 3, Indirapuram, Ghaziabad", "Cuisines: ": "Salad, Fast Food, Healthy Food, Juices", "hours": "8am\u20132am(Mon-Fri),8am\u20134am(Sat-Sun)", "Cost for two": "\u20b9500", "Featured in: ": "Ladies' Luncheon, Best Pizza Places In Town, Luxury Dining"}, {"Name": "Shiso & Yu Choi", "Rating": "4.4", "votes": "241", "location": " Shop 47, DLF City Court, Sikandarpur, Gurgaon", "Cuisines: ": "Chinese, Thai, Japanese", "hours": "12noon\u201312midnight(Mon-Sun)", "Cost for two": "\u20b91,500", "Featured in: ": "Sneak Peek Delhi"}, {"Name": "Public Headquarter", "Rating": "4.1", "votes": "293", "location": " 3, Community Center, PVR Anupam Complex, Saket, New Delhi", "Cuisines: ": "Finger Food, North Indian, North Eastern, Italian, Continental", "hours": "11am\u20131am(Mon-Sun)", "Cost for two": "\u20b91,500", "Featured in: ": "Best Bars and Pubs, Where's The Party?"}, {"Name": "Inferno Brewpub", "Rating": "4.3", "votes": "289", "location": " Plot 6 & 7, 3rd Floor, Sector 29, Gurgaon", "Cuisines: ": "North Indian, Chinese, Continental, Italian, Beverages", "hours": "12noon\u201312midnight(Mon-Sun)", "Cost for two": "\u20b91,800", "Featured in: ": "Microbreweries, Best Bars and Pubs, Get flat 30% OFF"}, {"Name": "Late Night Curry Boy", "Rating": "4.6", "votes": "105", "location": " 545A, Chirag Delhi, Hanuman Mandir Road, Greater Kailash 1 (GK 1), New Delhi", "Cuisines: ": "North Indian, Mughlai, Biryani, Rolls, Beverages", "hours": "6pm\u20135am(Mon-Sun)", "Cost for two": "\u20b9500", "Featured in: ": "Best of Delhi NCR, Trending This Week"}, {"Name": "TMH - The Maggi Hub", "Rating": "3.4", "votes": "32", "location": " 1st Floor, Behind Chimes Tower, Main Road, Vakil Market, Chakkarpur, DLF Phase 4, Gurgaon", "Cuisines: ": "Fast Food, Street Food, Beverages", "hours": "8am\u20134am(Mon-Sun)", "Cost for two": "\u20b9300", "Featured in: ": "Best of Delhi NCR, Trending This Week"}, {"Name": "The For'est", "Rating": "4.0", "votes": "160", "location": " 38, Basant Lok Community Centre, Vasant Vihar, New Delhi", "Cuisines: ": "Cafe, Asian, Korean, Beverages", "hours": "10am\u201310pm(Mon-Sun)", "Cost for two": "\u20b9700", "Featured in: ": "Best of Delhi NCR, Trending This Week"}, {"Name": "Desi Tadka", "Rating": "3.0", "votes": "46", "location": " Shop 5, Godavari Complex, Sector 52, Noida", "Cuisines: ": "North Indian", "hours": "11am\u20134pm,6:30pm\u201311pm(Mon-Sun)", "Cost for two": "\u20b9800", "Featured in: ": "Best of Delhi NCR, Trending This Week"}]