[{"Name": "Clubate", "Rating": "4.2", "votes": "781", "location": " 15, 2nd Floor, Eros Market Place, Shakti Khand 2, Indirapuram, Ghaziabad", "Cuisines: ": "North Indian, Chinese, Continental, Italian", "hours": "2pm\u201311:45pm(Mon-Sun)", "Cost for two": "\u20b91,200", "Featured in: ": "Best Bars and Pubs, New on Gold"}, {"Name": "TCK By The China Kitchen", "Rating": "4.3", "votes": "437", "location": " 11, Cyber Hub, Near DLF Cyber City, Gurgaon", "Cuisines: ": "Chinese", "hours": "12noon\u20134pm,6pm\u201311:30pm(Mon-Sun)", "Cost for two": "\u20b92,200", "Featured in: ": "Best Bars and Pubs, New on Gold"}, {"Name": "Charcha - When Coffee Met Cocktail", "Rating": "NEW", "votes": "437", "location": " F-15A, Ground Floor, Opposite NDPL, Vijay Nagar, New Delhi", "Cuisines: ": "Cafe, Chinese", "hours": "11am\u20131am(Mon-Sun)", "Cost for two": "\u20b9650", "Featured in: ": "Newly Opened"}, {"Name": "Tenali - The Andhra Kitchen", "Rating": "3.9", "votes": "138", "location": " Shop 31, 2nd Floor, Main Market, Green Park, New Delhi", "Cuisines: ": "Andhra", "hours": "12:30pm\u201310pm(Mon-Sun)", "Cost for two": "\u20b9800", "Featured in: ": "Newly Opened"}, {"Name": "Fig At Museo", "Rating": "4.0", "votes": "62", "location": " Museo Camera Centre Photographic Arts, Shri Ganesh Mandir Marg, Sector 28, DLF Phase 4, Gurgaon", "Cuisines: ": "Cafe, European, American, Continental, Italian, Desserts", "hours": "8am\u201311pm(Mon-Sun)", "Cost for two": "\u20b91,400", "Featured in: ": "Newly Opened"}, {"Name": "China Box", "Rating": "4.6", "votes": "577", "location": " 2nd Floor, Ashoka Complex, Near Ocus Quantum Mall, Sector 51, Near Sector 50, Gurgaon", "Cuisines: ": "Chinese", "hours": "11am\u20134am(Mon-Sun)", "Cost for two": "\u20b9600", "Featured in: ": "Best of Delhi NCR"}, {"Name": "Firangi Island", "Rating": "4.2", "votes": "442", "location": " 62, Rama Road, Kirti Nagar, New Delhi", "Cuisines: ": "North Indian, Chinese, Continental, Italian, Momos", "hours": "4pm\u20131am(Mon-Sun)", "Cost for two": "\u20b91,200", "Featured in: ": "Boozy Bars"}, {"Name": "Italiano", "Rating": "4.2", "votes": "1642", "location": " Cyber Hub, DLF Cyber City, Gurgaon", "Cuisines: ": "Italian, European, Pizza, Beverages", "hours": "12noon\u201311pm(Mon-Sun)", "Cost for two": "\u20b91,500", "Featured in: ": "Boozy Bars"}, {"Name": "Scoops", "Rating": "4.0", "votes": "811", "location": " E-1, Bal Udyan Road, Uttam Nagar, New Delhi", "Cuisines: ": "Beverages, Fast Food, Desserts", "hours": "7am\u20134am(Mon-Sun)", "Cost for two": "\u20b9600", "Featured in: ": "Boozy Bars"}, {"Name": "Mughal Affair", "Rating": "4.5", "votes": "418", "location": " 46, DLF City Court, Sikandarpur, Gurgaon", "Cuisines: ": "North Indian, Mughlai, Biryani, Rolls, Kebab", "hours": "12noon\u201311:30pm(Mon-Sun)", "Cost for two": "\u20b9650", "Featured in: ": "Food Hygiene Rated Restaurants, Best of Delhi NCR"}, {"Name": "Pikwik", "Rating": "4.0", "votes": "813", "location": " 66, Shakti Vihar, Pitampura, New Delhi", "Cuisines: ": "North Indian, Chinese, Mughlai", "hours": "11am\u201312midnight(Mon-Sun)", "Cost for two": "\u20b9850", "Featured in: ": "Irresistible Food"}, {"Name": "Bakingo", "Rating": "4.0", "votes": "415", "location": " Delivery Only", "Cuisines: ": "Bakery, Desserts", "hours": "8am\u201312midnight(Mon-Sun)", "Cost for two": "\u20b9300", "Featured in: ": "Irresistible Food"}, {"Name": "Hudson Chopsticks", "Rating": "4.2", "votes": "700", "location": " 84, Mall Road, Kingsway Camp, Delhi University, Delhi University-GTB Nagar, New Delhi", "Cuisines: ": "Asian, Chinese, Thai, Momos", "hours": "12noon\u201311pm(Mon-Sun)", "Cost for two": "\u20b9600", "Featured in: ": "Irresistible Food"}, {"Name": "Jaiveer Naan & Chaap", "Rating": "3.8", "votes": "1037", "location": " Shop 95, Aggarwal City Plaza, Near M2K, Rohini, New Delhi", "Cuisines: ": "North Indian, Fast Food, Rolls", "hours": "11am\u201311pm(Mon-Sun)", "Cost for two": "\u20b9500", "Featured in: ": "Irresistible Food"}, {"Name": "Three Tuns Cafe & Bar", "Rating": "4.2", "votes": "1150", "location": " 2nd Floor, Unity One Mall, Near Janak Puri West Metro Station, Janakpuri, New Delhi", "Cuisines: ": "Continental, North Indian, Italian, Chinese", "hours": "12noon\u201312midnight(Mon-Sun)", "Cost for two": "\u20b91,400", "Featured in: ": "Ladies' Luncheon, Great Buffets"}]