[{"Name": "Yummy Shop", "Rating": "3.8", "votes": "33", "location": " C-10/28, Near Manav Chowk, Sector 15, Rohini, New Delhi", "Cuisines: ": "Fast Food", "hours": "11am\u201311pm(Mon-Sun)", "Cost for two": "\u20b9400"}, {"Name": "Ashirwad Restaurant", "Rating": "3.2", "votes": "10", "location": " G-1, Dal Mil Road, Pillar 683 Uttam Nagar, New Delhi", "Cuisines: ": "North Indian", "hours": "10am\u20134pm,6pm\u201311:30pm(Mon-Sun)", "Cost for two": "\u20b9200"}, {"Name": "Pind Curry", "Rating": "3.2", "votes": "6", "location": " L1, Wave Mall, Sector 18, Noida", "Cuisines: ": "North Indian, Mughlai", "hours": "10am\u201310:30pm(Mon-Sun)", "Cost for two": "\u20b9450"}, {"Name": "Nutri Ville'", "Rating": "3.5", "votes": "17", "location": " DP-1, Top Floor, Chisel Gym, Opposite DAV School, Pitampura, New Delhi", "Cuisines: ": "Healthy Food, Beverages", "hours": "8am\u20139:30pm(Mon-Sat),Closed(Sun)", "Cost for two": "\u20b9400"}, {"Name": "Desi Thaat The Taste Of Haryana", "Rating": "3.2", "votes": "7", "location": " Vpo Kherki Daula, Near Inox Mall, Sector 84, Near Sector 83, Gurgaon", "Cuisines: ": "North Indian", "hours": "11am\u201311pm(Mon-Sun)", "Cost for two": "\u20b9250"}, {"Name": "X Hale Hookah Lounge", "Rating": "3.1", "votes": "7", "location": " Basement, Relance Plaza 2, Main Market, Sector 4, Vaishali, Ghaziabad", "Cuisines: ": "North Indian, Fast Food, Chinese", "hours": "12noon\u201310pm(Mon-Sun)", "Cost for two": "\u20b9600"}, {"Name": "It's Pizza Time", "Rating": "3.4", "votes": "18", "location": " Shop 2, RZA-37, Gali 2, Gandhi Market, Main Sagar Pur, Palam, New Delhi", "Cuisines: ": "Pizza", "hours": "11am\u201310:30pm(Mon-Sun)", "Cost for two": "\u20b9250"}, {"Name": "Brew Buddy", "Rating": "4.1", "votes": "1785", "location": " HUDA Market, Sector 29, Gurgaon", "Cuisines: ": "Bar Food, North Indian, Italian, Mexican, Chinese", "hours": "12noon\u201312midnight(Mon-Sun)", "Cost for two": "\u20b92,000", "Featured in: ": "Microbreweries, Where's The Party?"}, {"Name": "Big Banana", "Rating": "3.5", "votes": "166", "location": " 15 & 16, 1st Floor, J Block Market, Saket, New Delhi", "Cuisines: ": "North Indian, Mughlai, Chinese", "hours": "11:30am\u201311:30pm(Mon-Sun)", "Cost for two": "\u20b9900", "Featured in: ": "Microbreweries, Where's The Party?"}, {"Name": "Dosa Plaza", "Rating": "3.6", "votes": "38", "location": " 22, H-Block, Amity University Campus, Sector 125, Noida", "Cuisines: ": "South Indian, Chinese", "hours": "10am\u20139pm(Mon-Sun)", "Cost for two": "\u20b9400", "Featured in: ": "Microbreweries, Where's The Party?"}, {"Name": "Big Bake", "Rating": "3.8", "votes": "401", "location": " 8, Vaishali Enclave, Opposite Pillar 353, Main Metro Road, Pitampura, New Delhi", "Cuisines: ": "Chinese, Fast Food, Bakery", "hours": "9:30am\u20139pm(Mon-Sun)", "Cost for two": "\u20b9600", "Featured in: ": "Microbreweries, Where's The Party?"}, {"Name": "Apna Swaad", "Rating": "NEW", "votes": "401", "location": " 8 A/10, Gandhi Park, Hauz  Rani, Malviya Nagar, New Delhi", "Cuisines: ": "North Indian, Mughlai", "hours": "6pm\u20135am(Mon-Sun)", "Cost for two": "\u20b9250", "Featured in: ": "Microbreweries, Where's The Party?"}, {"Name": "Shri Radha Ki Rasoi", "Rating": "2.7", "votes": "223", "location": " B 222, Palam Extension, Sector 7, Dwarka, New Delhi", "Cuisines: ": "North Indian, Chinese", "hours": "11am\u20131am(Mon-Sun)", "Cost for two": "\u20b9450", "Featured in: ": "Microbreweries, Where's The Party?"}, {"Name": "Morning Meals", "Rating": "3.3", "votes": "10", "location": " Plot 82, 2nd Floor, Sector 44, Gurgaon", "Cuisines: ": "Healthy Food, North Indian", "hours": "7am\u20134am(Mon-Sun)", "Cost for two": "\u20b9400", "Featured in: ": "Microbreweries, Where's The Party?"}, {"Name": "Spice Wok", "Rating": "3.5", "votes": "109", "location": " B-147, Naveen Plaza, Sharma Market, Pul Pehladpur, Charmwood Village, Faridabad", "Cuisines: ": "North Indian, Chinese, Fast Food", "hours": "11am\u201310:30pm(Mon-Sun)", "Cost for two": "\u20b9550", "Featured in: ": "Microbreweries, Where's The Party?"}]